{"activeUsers":[{"total":0,"name":"Dec 12th"},{"total":0,"name":"Dec 13th"},{"total":0,"name":"Dec 14th"},{"total":0,"name":"Dec 15th"},{"total":0,"name":"Dec 16th"},{"total":0,"name":"Dec 17th"},{"total":0,"name":"Dec 18th"},{"total":0,"name":"Dec 19th"},{"total":0,"name":"Dec 20th"},{"total":0,"name":"Dec 21st"},{"total":0,"name":"Dec 22nd"},{"total":0,"name":"Dec 23rd"},{"total":58,"name":"Dec 24th","facebook":58},{"total":16,"name":"Dec 25th","facebook":16}],"genderUsage":[{"total":0,"name":"Dec 12th"},{"total":0,"name":"Dec 13th"},{"total":0,"name":"Dec 14th"},{"total":0,"name":"Dec 15th"},{"total":0,"name":"Dec 16th"},{"total":0,"name":"Dec 17th"},{"total":0,"name":"Dec 18th"},{"total":0,"name":"Dec 19th"},{"total":0,"name":"Dec 20th"},{"total":0,"name":"Dec 21st"},{"total":0,"name":"Dec 22nd"},{"total":0,"name":"Dec 23rd"},{"total":58,"name":"Dec 24th","male":58},{"total":16,"name":"Dec 25th","male":16}],"interactionsRange":[{"name":"[0-2]","count":0},{"name":"[2-4]","count":0},{"name":"[4-6]","count":0},{"name":"[6-10]","count":0},{"name":"[10-15]","count":0},{"name":"[15-30]","count":1},{"name":"[30-50]","count":0},{"name":"50+","count":1}],"fictiveSpecificMetrics":{"numberOfInteractionInAverage":37,"numberOfUsersToday":1,"numberOfUsersYesterday":1,"numberOfUsersThisWeek":1},"retentionHeatMap":{"Dec 17th":[0,0,0,0,0,0,0,0,0],"Dec 18th":[0,0,0,0,0,0,0,0,0],"Dec 19th":[0,0,0,0,0,0,0,null,0],"Dec 20th":[0,0,0,0,0,0,null,null,0],"Dec 21st":[0,0,0,0,0,null,null,null,0],"Dec 22nd":[0,0,0,0,null,null,null,null,0],"Dec 23rd":[0,0,0,null,null,null,null,null,0],"Dec 24th":[1,1,null,null,null,null,null,null,1]},"busyHoursHeatMap":{"Dec 25th":[0,0,0,0,0,0.08,0.32,0,0,0,0,0,0,0,0,0,0,0.75,0.28,0,0,0,0,0],"Dec 24th":[0,0,0,0,0,0,0.48,0.75,0,0,0,0,0,0,0,0,0.04,0.32,0.75,0,0,0,0,0],"Dec 23rd":[0,0,0,0,0,0,0,0,0,0,0,0,0,0,0,0,0,0,0,0,0,0,0,0],"Dec 22nd":[0,0,0,0,0,0,0,0,0,0,0,0,0,0,0,0,0,0,0,0,0,0,0,0],"Dec 21st":[0,0,0,0,0,0,0,0,0,0,0,0,0,0,0,0,0,0,0,0,0,0,0,0],"Dec 20th":[0,0,0,0,0,0,0,0,0,0,0,0,0,0,0,0,0,0,0,0,0,0,0,0],"Dec 19th":[0,0,0,0,0,0,0,0,0,0,0,0,0,0,0,0,0,0,0,0,0,0,0,0]},"totalUsers":[{"total":0,"facebook":0,"name":"Dec 23rd"},{"total":1,"facebook":1,"name":"Dec 24th"}]}